plaquette/__init__.py
plaquette/__main__.py
plaquette/graph.py
plaquette/pauli.py
plaquette/pauli_frame.py
plaquette/circuit/__init__.py
plaquette/circuit/generator.py
plaquette/circuit/openqasm.py
plaquette/codes/__init__.py
plaquette/codes/_utils.py
plaquette/decoders/__init__.py
plaquette/device/__init__.py
plaquette/device/_circuitsim.py
plaquette/device/_errortrackingbackend.py
plaquette/device/_stimsim.py
plaquette/errors/__init__.py
plaquette/errors/common_models.py
plaquette/frontend/__init__.py
plaquette/frontend/schemas.py
plaquette/visualizer/__init__.py
plaquette-0.1.1.post0.dist-info/LICENSE
plaquette-0.1.1.post0.dist-info/METADATA
plaquette-0.1.1.post0.dist-info/WHEEL
plaquette-0.1.1.post0.dist-info/entry_points.txt
plaquette-0.1.1.post0.dist-info/top_level.txt
plaquette-0.1.1.post0.dist-info/RECORD
