Metadata-Version: 2.1
Name: plaquette
Version: 0.1.1.post0
Summary: An all-encompassing quantum error-correction software package
Author-email: QC Design GmbH <software@qc.design>
Project-URL: Homepage, https://docs.plaquette.design
Project-URL: Bug Tracker, https://github.com/qc-design/plaquette/issues
Keywords: Quantum error correction,qec,quantum computing,fault tolerance
Classifier: Development Status :: 4 - Beta
Classifier: Intended Audience :: Developers
Classifier: Intended Audience :: Science/Research
Classifier: License :: OSI Approved :: Apache Software License
Classifier: Natural Language :: English
Classifier: Programming Language :: Python :: 3
Classifier: Programming Language :: Python :: 3.10
Requires-Python: >=3.10
License-File: LICENSE
Requires-Dist: fusion-blossom >=0.2.2
Requires-Dist: jsonschema >=4.16
Requires-Dist: matplotlib >=3.6.2
Requires-Dist: numpy >=1.23
Requires-Dist: pandas >=1.5.1
Requires-Dist: plotly >=5.11.0
Requires-Dist: pymatching >=2.0.1
Requires-Dist: PyYAML >=6.0
Requires-Dist: qiskit
Requires-Dist: qiskit-qasm3-import
Requires-Dist: pylatexenc
Requires-Dist: pydantic >=2.0
Requires-Dist: seaborn >=0.12.1
Requires-Dist: stim ~=1.12
Requires-Dist: toml >=0.10
Requires-Dist: tqdm
Requires-Dist: rustworkx
